{
	"configurations" : 
	[
		{
			"directories" : 
			[
				{
					"build" : ".",
					"jsonFile" : "directory-.-Debug-d0094a50bb2071803777.json",
					"minimumCMakeVersion" : 
					{
						"string" : "3.23"
					},
					"projectIndex" : 0,
					"source" : ".",
					"targetIndexes" : 
					[
						0
					]
				}
			],
			"name" : "Debug",
			"projects" : 
			[
				{
					"directoryIndexes" : 
					[
						0
					],
					"name" : "lab5_1",
					"targetIndexes" : 
					[
						0
					]
				}
			],
			"targets" : 
			[
				{
					"directoryIndex" : 0,
					"id" : "lab5_1::@6890427a1f51a3e7e1df",
					"jsonFile" : "target-lab5_1-Debug-f170388f05b6df0c3fa9.json",
					"name" : "lab5_1",
					"projectIndex" : 0
				}
			]
		}
	],
	"kind" : "codemodel",
	"paths" : 
	{
		"build" : "C:/Users/Slavcho/Desktop/Business/eCode/Structual Programming/Marija/SP-2023-2024/Class 3 (review and arrays & functions)/lab5/lab5_1/cmake-build-debug",
		"source" : "C:/Users/Slavcho/Desktop/Business/eCode/Structual Programming/Marija/SP-2023-2024/Class 3 (review and arrays & functions)/lab5/lab5_1"
	},
	"version" : 
	{
		"major" : 2,
		"minor" : 6
	}
}
